interp_tools/__init__.py
interp_tools/interp.py
interp_tools-2.0.1.dist-info/LICENSE
interp_tools-2.0.1.dist-info/METADATA
interp_tools-2.0.1.dist-info/WHEEL
interp_tools-2.0.1.dist-info/top_level.txt
interp_tools-2.0.1.dist-info/RECORD
