Metadata-Version: 2.2
Name: interp-tools
Version: 2.0.1
Summary: Interpolation Tool for 1d 2d and 3d functions
Home-page: https://github.com/antonianton228/interp-tools
Author: Mof1us
Author-email: antoon.s.ivanov@gmail.com
Keywords: interpolation,1d interpolation,2d interpolation,3d interpolation,functions,tools
Classifier: Programming Language :: Python :: 3.11
Classifier: License :: OSI Approved :: MIT License
Classifier: Operating System :: OS Independent
Requires-Python: >=3.7
License-File: LICENSE
Requires-Dist: numpy
Dynamic: author
Dynamic: author-email
Dynamic: classifier
Dynamic: description
Dynamic: description-content-type
Dynamic: home-page
Dynamic: keywords
Dynamic: requires-dist
Dynamic: requires-python
Dynamic: summary
